setup.py
AShareFactor/AshareFactor.py
AShareFactor/__init__.py
AshareFactor.egg-info/PKG-INFO
AshareFactor.egg-info/SOURCES.txt
AshareFactor.egg-info/dependency_links.txt
AshareFactor.egg-info/top_level.txt