Metadata-Version: 2.1
Name: AshareFactor
Version: 0.0.1
Summary: common A Share alpha and risk factors
Author: Xi
